pyvalet/__init__.py
pyvalet/exceptions.py
pyvalet/interpreter.py
pyvalet-1.1.1.dist-info/LICENSE
pyvalet-1.1.1.dist-info/WHEEL
pyvalet-1.1.1.dist-info/METADATA
pyvalet-1.1.1.dist-info/RECORD
