Metadata-Version: 2.1
Name: pyvalet
Version: 1.1.1
Summary: BoC Valet API Wrapper
Author-email: Tyler Roberts <tylerroberts.sgc@gmail.com>
Requires-Python: >=3.6
Classifier: Programming Language :: Python :: 3
Classifier: License :: OSI Approved :: MIT License
Classifier: Operating System :: OS Independent
Requires-Dist: pandas
Requires-Dist: urllib3==1.26.6
Requires-Dist: requests
Requires-Dist: loguru
Requires-Dist: pytest==5.2.1
Requires-Dist: pytest-cov==2.8.1
Requires-Dist: coverage-badge
Requires-Dist: coveralls
